MANIFEST.in
README.rst
requirements.txt
setup.py
src/utaskweb/__init__.py
src/utaskweb/common.py
src/utaskweb/kyomu.py
src/utaskweb/kyoshitsu.py
src/utaskweb/kyuko.py
src/utaskweb/version.py
src/utaskweb.egg-info/PKG-INFO
src/utaskweb.egg-info/SOURCES.txt
src/utaskweb.egg-info/dependency_links.txt
src/utaskweb.egg-info/pbr.json
src/utaskweb.egg-info/requires.txt
src/utaskweb.egg-info/top_level.txt