Metadata-Version: 1.1
Name: utaskweb
Version: 0.1.15
Summary: Utils for scraping and crawling UTask-web
Home-page: http://github.com/wkentaro/utaskweb
Author: Kentaro Wada
Author-email: www.kentaro.wada@gmail.com
License: MIT
Keywords: crawling scraping utility
Platform: UNKNOWN
Classifier: Development Status :: 5 - Production/Stable
Classifier: Intended Audience :: Developers
Classifier: License :: OSI Approved :: MIT License
Classifier: Operating System :: POSIX
Classifier: Topic :: Internet :: WWW/HTTP
